commandkit/EventManager.py
commandkit/__init__.py
commandkit/_parser.py
commandkit/commander.py
commandkit/core.py
commandkit/parser.py
commandkit-0.2.0.dist-info/LICENSE
commandkit-0.2.0.dist-info/METADATA
commandkit-0.2.0.dist-info/WHEEL
commandkit-0.2.0.dist-info/top_level.txt
commandkit-0.2.0.dist-info/RECORD
