Metadata-Version: 2.1
Name: commandkit
Version: 0.2.0
Summary: simple library to implement commands, events dispatchers
License: Copyright 2022 'programminglaboratorys'
Project-URL: Changelog, https://github.com/programminglaboratorys/commandkit/blob/main/CHANGELOG
Project-URL: Documentation, https://commandkit.readthedocs.io/en/latest/
Project-URL: Homepage, https://github.com/programminglaboratorys/commandkit
Project-URL: Issues, https://github.com/programminglaboratorys/commandkit/issues
Keywords: commands,python3,commandkit,events
Classifier: Intended Audience :: Developers
Classifier: Programming Language :: Python
Classifier: Programming Language :: Python :: 3
Classifier: Programming Language :: Python :: 3.10
Classifier: Programming Language :: Python :: 3.11
Classifier: Programming Language :: Python :: 3.12
Classifier: License :: OSI Approved :: MIT License
License-File: LICENSE
Provides-Extra: dev
Requires-Dist: black; extra == "dev"
Requires-Dist: sphinx; extra == "dev"
Requires-Dist: sphinx-rtd-theme; extra == "dev"
